{"name": "import itertools", "data": [[{"date": 1760109330, "score": 58}], [{"date": 1760109330, "score": 100}], [{"date": 1760109330, "score": 58}], [{"date": 1760109330, "score": 98}, {"date": 1760130796, "score": 91}], [{"date": 1760109330, "score": 253}], [{"date": 1760109330, "score": 53}], [{"date": 1760109330, "score": 72}, {"date": 1760358775, "score": 64}], [{"date": 1760109330, "score": 99}], [{"date": 1760109330, "score": 116}], [{"date": 1760109330, "score": 68}], [{"date": 1760109330, "score": 154}, {"date": 1760260454, "score": 153}, {"date": 1760368567, "score": 150}], [{"date": 1760109330, "score": 132}], [{"date": 1760109330, "score": 171}], [{"date": 1760109330, "score": 76}], [{"date": 1760109330, "score": 104}], [{"date": 1760109330, "score": 43}], [{"date": 1760109330, "score": 114}], [{"date": 1760109330, "score": 338}], [{"date": 1760109330, "score": 121}], [{"date": 1760109330, "score": 157}, {"date": 1760272102, "score": 156}], [{"date": 1760109330, "score": 59}], [{"date": 1760109330, "score": 106}], [{"date": 1760109330, "score": 225}], [{"date": 1760109330, "score": 62}], [{"date": 1760109330, "score": 187}], [{"date": 1760109330, "score": 54}], [{"date": 1760109330, "score": 125}], [{"date": 1760109330, "score": 84}, {"date": 1760206706, "score": 78}], [{"date": 1760109330, "score": 121}], [{"date": 1760109330, "score": 171}, {"date": 1760433469, "score": 123}], [{"date": 1760109330, "score": 50}], [{"date": 1760109330, "score": 39}], [{"date": 1760109330, "score": 79}], [{"date": 1760109330, "score": 202}, {"date": 1760476424, "score": 175}, {"date": 1760509439, "score": 172}], [{"date": 1760109330, "score": 92}], [{"date": 1760109330, "score": 96}], [{"date": 1760109330, "score": 125}, {"date": 1760358775, "score": 121}], [{"date": 1760109330, "score": 51}], [{"date": 1760109330, "score": 61}], [{"date": 1760109330, "score": 75}], [{"date": 1760109330, "score": 49}], [{"date": 1760109330, "score": 139}], [{"date": 1760109330, "score": 57}], [{"date": 1760109330, "score": 239}], [{"date": 1760109330, "score": 45}], [{"date": 1760109330, "score": 196}, {"date": 1760358775, "score": 192}], [{"date": 1760109330, "score": 55}], [{"date": 1760109330, "score": 128}], [{"date": 1760109330, "score": 87}], [{"date": 1760109330, "score": 100}], [{"date": 1760109330, "score": 115}], [{"date": 1760109330, "score": 40}], [{"date": 1760109330, "score": 21}], [{"date": 1760109330, "score": 309}], [{"date": 1760109330, "score": 114}], [{"date": 1760109330, "score": 42}], [{"date": 1760109330, "score": 54}], [{"date": 1760109330, "score": 138}], [{"date": 1760109330, "score": 180}, {"date": 1760358775, "score": 178}], [{"date": 1760109330, "score": 48}], [{"date": 1760109330, "score": 63}], [{"date": 1760109330, "score": 168}], [{"date": 1760109330, "score": 79}], [{"date": 1760109330, "score": 161}, {"date": 1760476424, "score": 156}], [{"date": 1760109330, "score": 116}, {"date": 1760358775, "score": 110}], [{"date": 1760109330, "score": 291}], [{"date": 1760109330, "score": 33}], [{"date": 1760109330, "score": 128}], [{"date": 1760109330, "score": 196}], [{"date": 1760109330, "score": 101}], [{"date": 1760109330, "score": 124}], [{"date": 1760109330, "score": 60}], [{"date": 1760109330, "score": 46}], [{"date": 1760109330, "score": 106}], [{"date": 1760109330, "score": 86}], [{"date": 1760109330, "score": 328}], [{"date": 1760109330, "score": 126}], [{"date": 1760109330, "score": 61}], [{"date": 1760109330, "score": 123}], [{"date": 1760109330, "score": 276}], [{"date": 1760109330, "score": 96}], [{"date": 1760109330, "score": 50}], [{"date": 1760109330, "score": 40}], [{"date": 1760109330, "score": 62}], [{"date": 1760109330, "score": 88}, {"date": 1760206706, "score": 86}], [{"date": 1760109330, "score": 224}], [{"date": 1760109330, "score": 36}], [{"date": 1760109330, "score": 110}], [{"date": 1760109330, "score": 286}], [{"date": 1760109330, "score": 207}], [{"date": 1760109330, "score": 63}], [{"date": 1760109330, "score": 101}], [{"date": 1760109330, "score": 101}], [{"date": 1760109330, "score": 115}], [{"date": 1760109330, "score": 84}], [{"date": 1760109330, "score": 309}], [{"date": 1760109330, "score": 117}], [{"date": 1760109330, "score": 99}], [{"date": 1760109330, "score": 134}], [{"date": 1760109330, "score": 96}], [{"date": 1760109330, "score": 326}], [{"date": 1760109330, "score": 178}, {"date": 1760272102, "score": 177}, {"date": 1760466194, "score": 175}], [{"date": 1760109330, "score": 29}], [{"date": 1760109330, "score": 94}], [{"date": 1760109330, "score": 190}], [{"date": 1760109330, "score": 75}], [{"date": 1760109330, "score": 245}, {"date": 1760368567, "score": 168}], [{"date": 1760109330, "score": 64}], [{"date": 1760109330, "score": 90}], [{"date": 1760109330, "score": 114}], [{"date": 1760109330, "score": 62}], [{"date": 1760109330, "score": 106}], [{"date": 1760109330, "score": 25}], [{"date": 1760109330, "score": 65}], [{"date": 1760109330, "score": 70}], [{"date": 1760109330, "score": 20}], [{"date": 1760109330, "score": 193}, {"date": 1760206706, "score": 192}], [{"date": 1760109330, "score": 280}], [{"date": 1760109330, "score": 127}, {"date": 1760272102, "score": 119}], [{"date": 1760109330, "score": 99}], [{"date": 1760109330, "score": 95}, {"date": 1760282000, "score": 90}], [{"date": 1760109330, "score": 82}], [{"date": 1760109330, "score": 75}], [{"date": 1760109330, "score": 126}, {"date": 1760293173, "score": 113}], [{"date": 1760109330, "score": 130}], [{"date": 1760109330, "score": 58}], [{"date": 1760109330, "score": 80}], [{"date": 1760109330, "score": 59}], [{"date": 1760109330, "score": 47}], [{"date": 1760109330, "score": 65}], [{"date": 1760109330, "score": 133}, {"date": 1760206706, "score": 132}], [{"date": 1760109330, "score": 126}], [{"date": 1760109330, "score": 321}], [{"date": 1760109330, "score": 181}], [{"date": 1760109330, "score": 32}], [{"date": 1760109330, "score": 107}], [{"date": 1760109330, "score": 144}], [{"date": 1760109330, "score": 117}], [{"date": 1760109330, "score": 100}], [{"date": 1760109330, "score": 36}], [{"date": 1760109330, "score": 100}], [{"date": 1760109330, "score": 40}], [{"date": 1760109330, "score": 213}], [{"date": 1760109330, "score": 59}], [{"date": 1760109330, "score": 240}], [{"date": 1760109330, "score": 58}], [{"date": 1760109330, "score": 87}], [{"date": 1760109330, "score": 153}], [{"date": 1760109330, "score": 80}], [{"date": 1760109330, "score": 30}], [{"date": 1760109330, "score": 113}], [{"date": 1760109330, "score": 40}], [{"date": 1760109330, "score": 171}], [{"date": 1760109330, "score": 107}], [{"date": 1760109330, "score": 18}], [{"date": 1760109330, "score": 186}], [{"date": 1760109330, "score": 247}], [{"date": 1760109330, "score": 325}], [{"date": 1760109330, "score": 149}, {"date": 1760120546, "score": 141}], [{"date": 1760109330, "score": 119}], [{"date": 1760109330, "score": 87}], [{"date": 1760109330, "score": 110}, {"date": 1760206706, "score": 109}], [{"date": 1760109330, "score": 148}, {"date": 1760272102, "score": 147}], [{"date": 1760109330, "score": 32}], [{"date": 1760109330, "score": 155}], [{"date": 1760109330, "score": 65}], [{"date": 1760109330, "score": 80}, {"date": 1760185678, "score": 72}], [{"date": 1760109330, "score": 116}], [{"date": 1760109330, "score": 143}], [{"date": 1760109330, "score": 201}], [{"date": 1760109330, "score": 51}], [{"date": 1760109330, "score": 20}], [{"date": 1760109330, "score": 222}], [{"date": 1760109330, "score": 109}, {"date": 1760185678, "score": 105}], [{"date": 1760109330, "score": 87}, {"date": 1760195568, "score": 75}], [{"date": 1760109330, "score": 76}, {"date": 1760195568, "score": 68}], [{"date": 1760109330, "score": 55}, {"date": 1760195568, "score": 54}], [{"date": 1760109330, "score": 71}, {"date": 1760206706, "score": 60}], [{"date": 1760109330, "score": 21}], [{"date": 1760109330, "score": 84}], [{"date": 1760109330, "score": 67}], [{"date": 1760109330, "score": 203}], [{"date": 1760109330, "score": 99}, {"date": 1760206706, "score": 98}], [{"date": 1760109330, "score": 129}], [{"date": 1760109330, "score": 156}, {"date": 1760130796, "score": 120}], [{"date": 1760109330, "score": 60}], [{"date": 1760109330, "score": 97}], [{"date": 1760109330, "score": 73}], [{"date": 1760109330, "score": 115}], [{"date": 1760109330, "score": 112}], [{"date": 1760109330, "score": 244}], [{"date": 1760109330, "score": 143}], [{"date": 1760109330, "score": 103}], [{"date": 1760109330, "score": 75}], [{"date": 1760109330, "score": 106}], [{"date": 1760109330, "score": 135}], [{"date": 1760109330, "score": 54}], [{"date": 1760109330, "score": 120}], [{"date": 1760109330, "score": 102}], [{"date": 1760109330, "score": 91}], [{"date": 1760109330, "score": 237}], [{"date": 1760109330, "score": 107}, {"date": 1760144874, "score": 105}], [{"date": 1760109330, "score": 73}], [{"date": 1760109330, "score": 157}, {"date": 1760445275, "score": 149}], [{"date": 1760109330, "score": 183}, {"date": 1760174052, "score": 180}], [{"date": 1760109330, "score": 149}], [{"date": 1760109330, "score": 86}], [{"date": 1760109330, "score": 223}], [{"date": 1760109330, "score": 324}], [{"date": 1760109330, "score": 20}], [{"date": 1760109330, "score": 48}], [{"date": 1760109330, "score": 117}], [{"date": 1760109330, "score": 89}], [{"date": 1760109330, "score": 73}], [{"date": 1760109330, "score": 48}], [{"date": 1760109330, "score": 154}, {"date": 1760455075, "score": 136}], [{"date": 1760109330, "score": 106}], [{"date": 1760109330, "score": 64}], [{"date": 1760109330, "score": 244}], [{"date": 1760109330, "score": 95}, {"date": 1760206706, "score": 94}], [{"date": 1760109330, "score": 101}], [{"date": 1760109330, "score": 144}], [{"date": 1760109330, "score": 53}, {"date": 1760174052, "score": 52}], [{"date": 1760109330, "score": 193}], [{"date": 1760109330, "score": 129}], [{"date": 1760109330, "score": 159}], [{"date": 1760109330, "score": 58}], [{"date": 1760109330, "score": 119}], [{"date": 1760109330, "score": 73}], [{"date": 1760109330, "score": 115}], [{"date": 1760109330, "score": 43}], [{"date": 1760109330, "score": 75}], [{"date": 1760109330, "score": 306}], [{"date": 1760109330, "score": 116}, {"date": 1760347167, "score": 114}], [{"date": 1760109330, "score": 67}], [{"date": 1760109330, "score": 60}], [{"date": 1760109330, "score": 79}], [{"date": 1760109330, "score": 245}], [{"date": 1760109330, "score": 104}], [{"date": 1760109330, "score": 160}], [{"date": 1760109330, "score": 21}], [{"date": 1760109330, "score": 54}], [{"date": 1760109330, "score": 80}], [{"date": 1760109330, "score": 63}], [{"date": 1760109330, "score": 141}, {"date": 1760185678, "score": 119}], [{"date": 1760109330, "score": 154}, {"date": 1760303580, "score": 114}], [{"date": 1760109330, "score": 103}], [{"date": 1760109330, "score": 80}], [{"date": 1760109330, "score": 26}], [{"date": 1760109330, "score": 117}], [{"date": 1760109330, "score": 97}], [{"date": 1760109330, "score": 59}], [{"date": 1760109330, "score": 150}], [{"date": 1760109330, "score": 102}], [{"date": 1760109330, "score": 322}], [{"date": 1760109330, "score": 105}], [{"date": 1760109330, "score": 82}], [{"date": 1760109330, "score": 61}], [{"date": 1760109330, "score": 86}], [{"date": 1760109330, "score": 140}], [{"date": 1760109330, "score": 47}], [{"date": 1760109330, "score": 39}], [{"date": 1760109330, "score": 142}], [{"date": 1760109330, "score": 209}], [{"date": 1760109330, "score": 134}], [{"date": 1760109330, "score": 125}], [{"date": 1760109330, "score": 56}], [{"date": 1760109330, "score": 263}], [{"date": 1760109330, "score": 74}], [{"date": 1760109330, "score": 119}], [{"date": 1760109330, "score": 94}], [{"date": 1760109330, "score": 108}], [{"date": 1760109330, "score": 132}, {"date": 1760217132, "score": 119}], [{"date": 1760109330, "score": 71}], [{"date": 1760109330, "score": 171}, {"date": 1760185678, "score": 166}], [{"date": 1760109330, "score": 38}], [{"date": 1760109330, "score": 243}], [{"date": 1760109330, "score": 118}], [{"date": 1760109330, "score": 133}], [{"date": 1760109330, "score": 212}, {"date": 1760185678, "score": 208}], [{"date": 1760109330, "score": 138}], [{"date": 1760109330, "score": 122}], [{"date": 1760109330, "score": 116}, {"date": 1760206706, "score": 106}], [{"date": 1760109330, "score": 227}], [{"date": 1760109330, "score": 297}], [{"date": 1760109330, "score": 117}], [{"date": 1760109330, "score": 75}], [{"date": 1760109330, "score": 90}, {"date": 1760195568, "score": 88}], [{"date": 1760109330, "score": 74}], [{"date": 1760109330, "score": 70}], [{"date": 1760109330, "score": 70}], [{"date": 1760109330, "score": 56}], [{"date": 1760109330, "score": 69}], [{"date": 1760109330, "score": 70}], [{"date": 1760109330, "score": 63}], [{"date": 1760109330, "score": 63}], [{"date": 1760109330, "score": 43}], [{"date": 1760109330, "score": 58}], [{"date": 1760109330, "score": 54}], [{"date": 1760109330, "score": 92}], [{"date": 1760109330, "score": 31}], [{"date": 1760109330, "score": 118}, {"date": 1760206706, "score": 116}], [{"date": 1760109330, "score": 65}], [{"date": 1760109330, "score": 92}], [{"date": 1760109330, "score": 64}], [{"date": 1760109330, "score": 88}], [{"date": 1760109330, "score": 51}], [{"date": 1760109330, "score": 248}], [{"date": 1760109330, "score": 38}], [{"date": 1760109330, "score": 87}], [{"date": 1760109330, "score": 32}], [{"date": 1760109330, "score": 45}, {"date": 1760130796, "score": 44}], [{"date": 1760109330, "score": 81}], [{"date": 1760109330, "score": 96}], [{"date": 1760109330, "score": 63}], [{"date": 1760109330, "score": 71}], [{"date": 1760109330, "score": 59}], [{"date": 1760109330, "score": 60}], [{"date": 1760109330, "score": 313}], [{"date": 1760109330, "score": 84}], [{"date": 1760109330, "score": 62}], [{"date": 1760109330, "score": 48}], [{"date": 1760109330, "score": 125}, {"date": 1760347167, "score": 119}], [{"date": 1760109330, "score": 242}], [{"date": 1760109330, "score": 205}], [{"date": 1760109330, "score": 30}], [{"date": 1760109330, "score": 69}, {"date": 1760130796, "score": 67}], [{"date": 1760109330, "score": 169}], [{"date": 1760109330, "score": 54}], [{"date": 1760109330, "score": 218}, {"date": 1760206706, "score": 206}], [{"date": 1760109330, "score": 87}], [{"date": 1760109330, "score": 64}], [{"date": 1760109330, "score": 101}], [{"date": 1760109330, "score": 76}], [{"date": 1760109330, "score": 154}, {"date": 1760303580, "score": 116}], [{"date": 1760109330, "score": 114}], [{"date": 1760109330, "score": 46}], [{"date": 1760109330, "score": 98}], [{"date": 1760109330, "score": 37}], [{"date": 1760109330, "score": 158}, {"date": 1760206706, "score": 155}], [{"date": 1760109330, "score": 148}, {"date": 1760272102, "score": 122}], [{"date": 1760109330, "score": 122}, {"date": 1760217132, "score": 120}], [{"date": 1760109330, "score": 65}], [{"date": 1760109330, "score": 79}], [{"date": 1760109330, "score": 93}], [{"date": 1760109330, "score": 55}], [{"date": 1760109330, "score": 54}], [{"date": 1760109330, "score": 108}], [{"date": 1760109330, "score": 252}], [{"date": 1760109330, "score": 100}], [{"date": 1760109330, "score": 67}], [{"date": 1760109330, "score": 89}], [{"date": 1760109330, "score": 127}], [{"date": 1760109330, "score": 127}], [{"date": 1760109330, "score": 105}], [{"date": 1760109330, "score": 113}], [{"date": 1760109330, "score": 100}], [{"date": 1760109330, "score": 111}], [{"date": 1760109330, "score": 64}], [{"date": 1760109330, "score": 45}], [{"date": 1760109330, "score": 204}], [{"date": 1760109330, "score": 69}], [{"date": 1760109330, "score": 231}, {"date": 1760217132, "score": 227}], [{"date": 1760109330, "score": 218}], [{"date": 1760109330, "score": 162}, {"date": 1760445275, "score": 125}, {"date": 1760455075, "score": 123}], [{"date": 1760109330, "score": 374}], [{"date": 1760109330, "score": 129}], [{"date": 1760109330, "score": 173}], [{"date": 1760109330, "score": 139}], [{"date": 1760109330, "score": 278}, {"date": 1760217132, "score": 274}], [{"date": 1760109330, "score": 127}, {"date": 1760206706, "score": 125}], [{"date": 1760109330, "score": 48}], [{"date": 1760109330, "score": 39}], [{"date": 1760109330, "score": 116}], [{"date": 1760109330, "score": 53}], [{"date": 1760109330, "score": 30}], [{"date": 1760109330, "score": 72}], [{"date": 1760109330, "score": 145}], [{"date": 1760109330, "score": 171}], [{"date": 1760109330, "score": 27}], [{"date": 1760109330, "score": 92}], [{"date": 1760109330, "score": 191}], [{"date": 1760109330, "score": 136}, {"date": 1760217132, "score": 134}], [{"date": 1760109330, "score": 68}], [{"date": 1760109330, "score": 25}], [{"date": 1760109330, "score": 54}], [{"date": 1760109330, "score": 215}], [{"date": 1760109330, "score": 61}], [{"date": 1760109330, "score": 57}], [{"date": 1760109330, "score": 107}], [{"date": 1760109330, "score": 63}], [{"date": 1760109330, "score": 156}], [{"date": 1760109330, "score": 63}], [{"date": 1760109330, "score": 100}], [{"date": 1760109330, "score": 59}], [{"date": 1760109330, "score": 250}, {"date": 1760195568, "score": 243}, {"date": 1760466194, "score": 223}], [{"date": 1760109330, "score": 146}, {"date": 1760120546, "score": 142}], [{"date": 1760109330, "score": 80}, {"date": 1760120546, "score": 79}], [{"date": 1760109330, "score": 64}], [{"date": 1760109330, "score": 67}]]}